MANIFEST.in
setup.cfg
setup.py
my_demo_617_20201114_06.egg-info/PKG-INFO
my_demo_617_20201114_06.egg-info/SOURCES.txt
my_demo_617_20201114_06.egg-info/dependency_links.txt
my_demo_617_20201114_06.egg-info/top_level.txt
tmp617_test/__init__.py
tmp617_test/main.py