Metadata-Version: 1.0
Name: my-demo-617-20201114-06
Version: 2020.11.14.6
Summary: A demo for python packaging.
Home-page: https://github.com/***/***
Author: liuyaqi
Author-email: yaqi_617@163.com
License: JD
Keywords: demo
Platform: UNKNOWN
